<?xml version="1.0" encoding="UTF-8" standalone="yes"?><title-info rev="0"><id>NPHB00208</id><console>ps3</console><media-type>edi</media-type><name>Fairytale Fights™ 'White Room' Teaser Demo</name><name lang="1">Fairytale Fights™ 'White Room' Teaser Demo</name><name lang="2">Démo Avant-Première Fairytale Fights™ &quot;Chambre blanche&quot;</name><name lang="3">Demo “Habitación blanca” de avance de Fairytale Fights™</name><name lang="4">Fairytale Fights™ 'White Room' Teaser Demo</name><name lang="5">Demo promozionale “Sala bianca” di Fairytale Fights™</name><parental-level>9</parental-level><icon type="320x176">http://tmdb.np.dl.playstation.net/tmdb/NPHB00208_00_6400573FB512985AB3042CF2D1F840AA1F643D26/ICON0.PNG</icon><resolution>480,576,720,480SQ,576SQ</resolution><sound-format>2LPCM,5.1LPCM,Dolby</sound-format></title-info>