<?xml version="1.0" encoding="UTF-8" standalone="yes"?><title-info rev="2"><id>BLUS30092</id><console>ps3</console><media-type>disc</media-type><name>Devil May Cry 4</name><name lang="0">Devil May Cry 4</name><name lang="1">Devil May Cry 4</name><name lang="2">Devil May Cry 4</name><name lang="3">Devil May Cry 4</name><name lang="4">Devil May Cry 4</name><name lang="5">Devil May Cry 4</name><name lang="6">Devil May Cry 4</name><name lang="7">Devil May Cry 4</name><name lang="8">Devil May Cry 4</name><name lang="9">Devil May Cry 4</name><name lang="10">Devil May Cry 4</name><name lang="11">Devil May Cry 4</name><name lang="12">Devil May Cry 4</name><name lang="13">Devil May Cry 4</name><name lang="14">Devil May Cry 4</name><name lang="15">Devil May Cry 4</name><parental-level>9</parental-level><icon type="320x176">http://tmdb.np.dl.playstation.net/tmdb/BLUS30092_00_15DA32013E59AE5DA7BD536F580C52B5B8184920/ICON0.PNG</icon><resolution>480,576,720,480SQ,576SQ</resolution><sound-format>2LPCM,5.1LPCM,Dolby</sound-format></title-info>