<?xml version="1.0" encoding="UTF-8" standalone="yes"?><title-info rev="1"><id>NPUB30581</id><console>ps3</console><media-type>edi</media-type><name>SONIC THE HEDGEHOG 4 Episode II</name><name lang="0">SONIC THE HEDGEHOG 4 Episode II</name><name lang="1">SONIC THE HEDGEHOG 4 Episode II</name><name lang="2">SONIC THE HEDGEHOG 4 Episode II</name><name lang="3">SONIC THE HEDGEHOG 4 Episode II</name><name lang="4">SONIC THE HEDGEHOG 4 Episode II</name><name lang="5">SONIC THE HEDGEHOG 4 Episode II</name><parental-level>3</parental-level><icon type="320x176">http://tmdb.np.dl.playstation.net/tmdb/NPUB30581_00_FDDEA11DD34029B846C51E96DE7D8D34F3B33A6C/ICON0.PNG</icon><resolution>480,576,720,1080,480SQ,576SQ</resolution><sound-format>2LPCM</sound-format></title-info>