<?xml version="1.0" encoding="UTF-8" standalone="yes"?><title-info rev="0"><id>NPEA00361</id><console>ps3</console><media-type>edi</media-type><name>Carnival Island (Digital)</name><name lang="2">Carnival Island (Version Digitale)</name><name lang="3">Carnival Island (Versión Digital)</name><name lang="4">Carnival Island (Digital)</name><name lang="5">Carnival Island: Il Magico Lunapark (Versione Digitale)</name><name lang="6">Carnival Island (Digital Versie)</name><name lang="7">Carnival Island (Versão Digital)</name><name lang="8">Веселая Ярмарка (Цифровая Версия)</name><name lang="12">Carnival Island (Digitaalinen)</name><name lang="13">Carnival Island (Digital Utgåva)</name><name lang="14">Carnival Island (Digital Udgave)</name><name lang="15">Carnival Island (Digital Utgave)</name><name lang="16">Carnival Island: Wesołe Miasteczko (Wersja Cyfrowa)</name><parental-level>3</parental-level><icon type="320x176">http://tmdb.np.dl.playstation.net/tmdb/NPEA00361_00_983C2857E0E51B4D4D47EF6FBC8D48591285EE2E/ICON0.PNG</icon><resolution>480,576,720,480SQ,576SQ</resolution><sound-format>2LPCM,5.1LPCM,7.1LPCM,Dolby,DTS</sound-format></title-info>