{"revision":4,"patchRevision":22,"formatVersion":4,"npTitleId":"CUSA01338_00","console":"PS4","names":[{"name":"Project CARS"},{"name":"Project CARS","lang":"fr"},{"name":"Project CARS","lang":"es"},{"name":"Project CARS","lang":"de"},{"name":"Project CARS","lang":"it"},{"name":"Project CARS","lang":"ru"},{"name":"Project CARS","lang":"pl"},{"name":"Project CARS","lang":"pt-BR"},{"name":"Project CARS","lang":"es-MX"}],"icons":[{"icon":"http://gs2-sec.ww.prod.dl.playstation.net/gs2-sec/appkgo/prod/CUSA01338_00/4/i_bc6c7f55f42e1cb205c423549b80ca1d551ecfbd2f04f8168517ce0f38529d07/i/icon0.png","type":"512x512"}],"parentalLevel":3,"pronunciation":"http://gs2-sec.ww.prod.dl.playstation.net/gs2-sec/appkgo/prod/CUSA01338_00/4/i_bc6c7f55f42e1cb205c423549b80ca1d551ecfbd2f04f8168517ce0f38529d07/i/pronunciation.xml","contentId":"UP0700-CUSA01338_00-PROJECTCARS00000","category":"gd","psVr":0,"neoEnable":0}
