<?xml version="1.0" encoding="UTF-8" standalone="yes"?><title-info rev="0"><id>BLES01492</id><console>ps3</console><media-type>disc</media-type><name>Sacred 3</name><name lang="0">Sacred 3</name><name lang="1">Sacred 3</name><name lang="2">Sacred 3</name><name lang="3">Sacred 3</name><name lang="4">Sacred 3</name><name lang="5">Sacred 3</name><name lang="6">Sacred 3</name><name lang="7">Sacred 3</name><name lang="8">Sacred 3</name><name lang="9">Sacred 3</name><name lang="10">Sacred 3</name><name lang="11">Sacred 3</name><name lang="12">Sacred 3</name><name lang="13">Sacred 3</name><name lang="14">Sacred 3</name><name lang="15">Sacred 3</name><name lang="16">Sacred 3</name><name lang="17">Sacred 3</name><name lang="18">Sacred 3</name><name lang="19">Sacred 3</name><parental-level>7</parental-level><icon type="320x176">http://tmdb.np.dl.playstation.net/tmdb/BLES01492_00_731A0EDC8BEECFA8400BB4338E19D69CF4ECBA76/ICON0.PNG</icon><resolution>480,576,720,480SQ,576SQ</resolution><sound-format>2LPCM,5.1LPCM,7.1LPCM,Dolby,DTS</sound-format></title-info>