<?xml version="1.0" encoding="UTF-8" standalone="yes"?><title-info rev="0"><id>NPEB02027</id><console>ps3</console><media-type>edi</media-type><name>Diablo III: Reaper of Souls – Ultimate Evil Edition</name><name lang="8">Diablo III: Reaper of Souls – Ultimate Evil Edition (русский)</name><name lang="16">Diablo III: Reaper of Souls – Ultimate Evil Edition (polski)</name><parental-level>9</parental-level><icon type="320x176">http://tmdb.np.dl.playstation.net/tmdb/NPEB02027_00_C1EF3BE5AB874D3EABEDF63D430A9CB769FB5B9C/ICON0.PNG</icon><resolution>480,576,720,480SQ,576SQ</resolution><sound-format>2LPCM,5.1LPCM,7.1LPCM,Dolby,DTS</sound-format></title-info>