<?xml version="1.0" encoding="UTF-8" standalone="yes"?><title-info rev="0"><id>NPEA00450</id><console>ps3</console><media-type>edi</media-type><name>Soul Sacrifice™ Original Soundtrack</name><name lang="2">Soul Sacrifice™ Bande Originale</name><name lang="3">Soul Sacrifice™  Banda Sonora Original</name><name lang="4">Soul Sacrifice™: Jagd durch die Zeit  Original-Soundtrack</name><name lang="5">Soul Sacrifice™ Colonna Sonora Originale</name><name lang="6">Soul Sacrifice™ Originele Soundtrack</name><name lang="7">Soul Sacrifice™ Banda Sonora Original</name><name lang="8">Soul Sacrifice™: Прыжок во времени Оригинальный Саундтрек</name><name lang="12">Soul Sacrifice™ Alkuperäinen ääniraita</name><name lang="13">Soul Sacrifice™ Originalsoundtrack</name><name lang="14">Soul Sacrifice™ Originalt Lydspor</name><name lang="15">Soul Sacrifice™ Originalsoundtrack</name><parental-level>8</parental-level><icon type="320x176">http://tmdb.np.dl.playstation.net/tmdb/NPEA00450_00_C30D3B2DF4BD382972340EE00B1CA352B8654B8A/ICON0.PNG</icon><resolution>480,576,720,1080,480SQ,576SQ</resolution><sound-format>2LPCM</sound-format></title-info>