<?xml version="1.0" encoding="UTF-8" standalone="yes"?><title-info rev="1"><id>NPUB30807</id><console>ps3</console><media-type>edi</media-type><name>LEGO® Batman™ 2: DC Super Heroes</name><name lang="1">LEGO® Batman™ 2: DC Super Heroes</name><name lang="2">LEGO® Batman™ 2: DC Super Heroes</name><name lang="3">LEGO® Batman™ 2: DC Super Heroes</name><name lang="8">LEGO® Batman™ 2: DC Super Heroes</name><name lang="17">LEGO® Batman™ 2: DC Super Heroes</name><parental-level>4</parental-level><icon type="320x176">http://tmdb.np.dl.playstation.net/tmdb/NPUB30807_00_F83999001E685249D4165FE7AD69FC1E2DF5EDB9/ICON0.PNG</icon><icon type="320x176" lang="1">http://tmdb.np.dl.playstation.net/tmdb/NPUB30807_00_F83999001E685249D4165FE7AD69FC1E2DF5EDB9/ICON0_01.PNG</icon><icon type="320x176" lang="2">http://tmdb.np.dl.playstation.net/tmdb/NPUB30807_00_F83999001E685249D4165FE7AD69FC1E2DF5EDB9/ICON0_02.PNG</icon><icon type="320x176" lang="3">http://tmdb.np.dl.playstation.net/tmdb/NPUB30807_00_F83999001E685249D4165FE7AD69FC1E2DF5EDB9/ICON0_03.PNG</icon><resolution>480,576,720,1080,480SQ,576SQ</resolution><sound-format>2LPCM,7.1LPCM,Dolby</sound-format></title-info>